rtl/alu.v
module alu (
    input [31:0] operand_a,
    input [31:0] operand_b,
    input [3:0] alu_control,
    output reg [31:0] result,
    output     zero
);

always@(*)begin
    result = 32'b0;
    case(alu_control)
    4'b0000 : result = (operand_a + operand_b); // add
    4'b0001 : result = (operand_a - operand_b); // sub
    4'b0010 : result = (operand_a & operand_b); // and
    4'b0011 : result = (operand_a | operand_b); // or
    4'b0100 : result = (operand_a ^ operand_b); // xor
    4'b0101 : result = (operand_a << operand_b[4:0]); // sll
    4'b0110 : result = (operand_a >> operand_b[4:0]); // srl
    4'b0111 : result = ($signed(operand_a) >>> operand_b[4:0]); // sra
    4'b1000 : result = ($signed(operand_a) < $signed(operand_b)) ? 32'b1 : 32'b0; // slt
    4'b1001 : result = (operand_a < operand_b) ? 32'b1 : 32'b0; // sltu
    default : result = 32'b0;
    endcase
end

assign zero =(result == 32'b0);

endmodule

tb/module_tb/alu_tb.v
`timescale 1ns/1ps

module alu_tb;

    //==================================================
    // Testbench Signals
    //==================================================

    reg  [31:0] operand_a;
    reg  [31:0] operand_b;
    reg  [3:0]  alu_control;

    wire [31:0] result;
    wire        zero;

    //==================================================
    // DUT
    //==================================================

    alu dut(
        .operand_a(operand_a),
        .operand_b(operand_b),
        .alu_control(alu_control),
        .result(result),
        .zero(zero)
    );

    //==================================================
    // Dump Waves
    //==================================================

    initial begin
        $dumpfile("alu_tb.vcd");
        $dumpvars(0, alu_tb);
    end

    //==================================================
    // Monitor
    //==================================================

    initial begin
        $monitor("T=%0t CTRL=%b A=%h B=%h RESULT=%h ZERO=%b",
                 $time,
                 alu_control,
                 operand_a,
                 operand_b,
                 result,
                 zero);
    end

    //==================================================
    // Test Sequence
    //==================================================

    initial begin

    //---------------- ADD ----------------
    operand_a   = 20;
    operand_b   = 30;
    alu_control = 4'b0000;
    #5;

    if(result == 50)
        $display("PASS : ADD");
    else
        $display("FAIL : ADD");

    //---------------- SUB ----------------
    operand_a   = 30;
    operand_b   = 20;
    alu_control = 4'b0001;
    #5;

    if(result == 10)
        $display("PASS : SUB");
    else
        $display("FAIL : SUB");

    //---------------- AND ----------------
    operand_a   = 32'hF0F0F0F0;
    operand_b   = 32'hFFFF0000;
    alu_control = 4'b0010;
    #5;

    if(result == 32'hF0F00000)
        $display("PASS : AND");
    else
        $display("FAIL : AND");

    //---------------- OR ----------------
    operand_a   = 32'hF0F00000;
    operand_b   = 32'h0000FFFF;
    alu_control = 4'b0011;
    #5;

    if(result == 32'hF0F0FFFF)
        $display("PASS : OR");
    else
        $display("FAIL : OR");

    //---------------- XOR ----------------
    operand_a   = 32'hAAAAAAAA;
    operand_b   = 32'h55555555;
    alu_control = 4'b0100;
    #5;

    if(result == 32'hFFFFFFFF)
        $display("PASS : XOR");
    else
        $display("FAIL : XOR");

    //---------------- SLL ----------------
    operand_a   = 32'h00000001;
    operand_b   = 5;
    alu_control = 4'b0101;
    #5;

    if(result == 32'h00000020)
        $display("PASS : SLL");
    else
        $display("FAIL : SLL");

    //---------------- SRL ----------------
    operand_a   = 32'h80000000;
    operand_b   = 4;
    alu_control = 4'b0110;
    #5;

    if(result == 32'h08000000)
        $display("PASS : SRL");
    else
        $display("FAIL : SRL");

    //---------------- SRA ----------------
    operand_a   = 32'h80000000;
    operand_b   = 4;
    alu_control = 4'b0111;
    #5;

    if(result == 32'hF8000000)
        $display("PASS : SRA");
    else
        $display("FAIL : SRA");

    //---------------- SLT ----------------
    operand_a   = -5;
    operand_b   = 10;
    alu_control = 4'b1000;
    #5;

    if(result == 1)
        $display("PASS : SLT");
    else
        $display("FAIL : SLT");

    //---------------- SLTU ----------------
    operand_a   = 32'hFFFFFFFF;
    operand_b   = 32'h00000001;
    alu_control = 4'b1001;
    #5;

    if(result == 0)
        $display("PASS : SLTU");
    else
        $display("FAIL : SLTU");

    //---------------- ZERO FLAG ----------------
    operand_a   = 55;
    operand_b   = 55;
    alu_control = 4'b0001;
    #5;

    if(result == 0 && zero)
        $display("PASS : ZERO FLAG");
    else
        $display("FAIL : ZERO FLAG");

    //---------------- DEFAULT ----------------
    operand_a   = 10;
    operand_b   = 20;
    alu_control = 4'b1111;
    #5;

    if(result == 0)
        $display("PASS : DEFAULT");
    else
        $display("FAIL : DEFAULT");

    //-------------------------------------
    $display("--------------------------------");
    $display("ALU TEST COMPLETED");
    $display("--------------------------------");

    $finish;

    end

endmodule

vcd/alu_tb.vcd
$date
	Thu Jul 02 13:33:31 2026
$end
$version
	Icarus Verilog
$end
$timescale
	1ps
$end
$scope module alu_tb $end
$var wire 32 ! result [31:0] $end
$var wire 1 " zero $end
$var reg 4 # alu_control [3:0] $end
$var reg 32 $ operand_a [31:0] $end
$var reg 32 % operand_b [31:0] $end
$scope module dut $end
$var wire 4 & alu_control [3:0] $end
$var wire 32 ' operand_a [31:0] $end
$var wire 32 ( operand_b [31:0] $end
$var wire 1 " zero $end
$var reg 32 ) result [31:0] $end
$upscope $end
$upscope $end
$enddefinitions $end
#0
$dumpvars
b110010 )
b11110 (
b10100 '
b0 &
b11110 %
b10100 $
b0 #
0"
b110010 !
$end
#5000
b1010 )
0"
b1010 !
b1 #
b1 &
b10100 %
b10100 (
b11110 $
b11110 '
#10000
b11110000111100000000000000000000 )
0"
b11110000111100000000000000000000 !
b10 #
b10 &
b11111111111111110000000000000000 %
b11111111111111110000000000000000 (
b11110000111100001111000011110000 $
b11110000111100001111000011110000 '
#15000
b11110000111100001111111111111111 )
0"
b11110000111100001111111111111111 !
b11 #
b11 &
b1111111111111111 %
b1111111111111111 (
b11110000111100000000000000000000 $
b11110000111100000000000000000000 '
#20000
b11111111111111111111111111111111 )
0"
b11111111111111111111111111111111 !
b100 #
b100 &
b1010101010101010101010101010101 %
b1010101010101010101010101010101 (
b10101010101010101010101010101010 $
b10101010101010101010101010101010 '
#25000
b100000 )
0"
b100000 !
b101 #
b101 &
b101 %
b101 (
b1 $
b1 '
#30000
b1000000000000000000000000000 )
0"
b1000000000000000000000000000 !
b110 #
b110 &
b100 %
b100 (
b10000000000000000000000000000000 $
b10000000000000000000000000000000 '
#35000
b11111000000000000000000000000000 )
0"
b11111000000000000000000000000000 !
b111 #
b111 &
#40000
b1 )
0"
b1 !
b1000 #
b1000 &
b1010 %
b1010 (
b11111111111111111111111111111011 $
b11111111111111111111111111111011 '
#45000
b0 )
1"
b0 !
b1001 #
b1001 &
b1 %
b1 (
b11111111111111111111111111111111 $
b11111111111111111111111111111111 '
#50000
b1 #
b1 &
b110111 %
b110111 (
b110111 $
b110111 '
#55000
b1111 #
b1111 &
b10100 %
b10100 (
b1010 $
b1010 '
