rtl/alu_control.v
module alu_control (
    input [6:0] opcode,
    input [2:0] funct3,
    input [6:0] funct7,
    output reg [3:0] alu_control
);
always @(*) begin
    alu_control = 4'b0000; // default ADD (for LUI, AUIPC, JAL, JALR)
    case(opcode)
        7'b0110011: begin // R-type
            case({funct7, funct3})
                10'b0000000000: alu_control = 4'b0000; // add
                10'b0100000000: alu_control = 4'b0001; // sub
                10'b0000000111: alu_control = 4'b0010; // and
                10'b0000000110: alu_control = 4'b0011; // or
                10'b0000000100: alu_control = 4'b0100; // xor
                10'b0000000001: alu_control = 4'b0101; // sll
                10'b0000000101: alu_control = 4'b0110; // srl
                10'b0100000101: alu_control = 4'b0111; // sra
                10'b0000000010: alu_control = 4'b1000; // slt
                10'b0000000011: alu_control = 4'b1001; // sltu
                default: alu_control = 4'b1111;
            endcase
        end
        7'b0010011: begin // I-type ALU
            case(funct3)
                3'b000: alu_control = 4'b0000; // addi
                3'b111: alu_control = 4'b0010; // andi
                3'b110: alu_control = 4'b0011; // ori
                3'b100: alu_control = 4'b0100; // xori
                3'b010: alu_control = 4'b1000; // slti
                3'b011: alu_control = 4'b1001; // sltiu
                3'b001: begin
                    if(funct7 == 7'b0000000) alu_control = 4'b0101; // slli
                    else alu_control = 4'b1111;
                end
                3'b101: begin
                    if(funct7 == 7'b0000000) alu_control = 4'b0110; // srli
                    else if(funct7 == 7'b0100000) alu_control = 4'b0111; // srai
                    else alu_control = 4'b1111;
                end
                default: alu_control = 4'b1111;
            endcase
        end
        7'b0000011: // Load
            alu_control = 4'b0000;
        7'b0100011: // Store
            alu_control = 4'b0000;
        7'b1100011: // Branch
            case(funct3)
                3'b000, 3'b001: alu_control = 4'b0001; // beq/bne (sub)
                3'b100, 3'b101: alu_control = 4'b1000; // blt/bge (slt)
                3'b110, 3'b111: alu_control = 4'b1001; // bltu/bgeu (sltu)
                default: alu_control = 4'b1111;
            endcase
        7'b0110111, 7'b0010111, 7'b1101111, 7'b1100111: // LUI, AUIPC, JAL, JALR
            alu_control = 4'b0000; // ADD
        default:
            alu_control = 4'b1111;
    endcase
end
endmodule

tb/module_tb/alu_control_tb.v
`timescale 1ns/1ps

module alu_control_tb;

    reg  [6:0] opcode;
    reg  [2:0] funct3;
    reg  [6:0] funct7;

    wire [3:0] alu_control;

    alu_control dut(
        .opcode(opcode),
        .funct3(funct3),
        .funct7(funct7),
        .alu_control(alu_control)
    );

    initial begin
        $dumpfile("alu_control_tb.vcd");
        $dumpvars(0, alu_control_tb);
    end

    initial begin
        $monitor("T=%0t OPCODE=%b FUNCT3=%b FUNCT7=%b ALUCTRL=%b",
                 $time, opcode, funct3, funct7, alu_control);
    end

    initial begin

    //-------------------------
    // R-Type
    //-------------------------

    opcode=7'b0110011;

    // ADD
    funct7=7'b0000000; funct3=3'b000; #5;
    if(alu_control==4'b0000) $display("PASS : ADD");
    else $display("FAIL : ADD");

    // SUB
    funct7=7'b0100000; funct3=3'b000; #5;
    if(alu_control==4'b0001) $display("PASS : SUB");
    else $display("FAIL : SUB");

    // AND
    funct7=7'b0000000; funct3=3'b111; #5;
    if(alu_control==4'b0010) $display("PASS : AND");
    else $display("FAIL : AND");

    // OR
    funct7=7'b0000000; funct3=3'b110; #5;
    if(alu_control==4'b0011) $display("PASS : OR");
    else $display("FAIL : OR");

    // XOR
    funct7=7'b0000000; funct3=3'b100; #5;
    if(alu_control==4'b0100) $display("PASS : XOR");
    else $display("FAIL : XOR");

    // SLL
    funct7=7'b0000000; funct3=3'b001; #5;
    if(alu_control==4'b0101) $display("PASS : SLL");
    else $display("FAIL : SLL");

    // SRL
    funct7=7'b0000000; funct3=3'b101; #5;
    if(alu_control==4'b0110) $display("PASS : SRL");
    else $display("FAIL : SRL");

    // SRA
    funct7=7'b0100000; funct3=3'b101; #5;
    if(alu_control==4'b0111) $display("PASS : SRA");
    else $display("FAIL : SRA");

    // SLT
    funct7=7'b0000000; funct3=3'b010; #5;
    if(alu_control==4'b1000) $display("PASS : SLT");
    else $display("FAIL : SLT");

    // SLTU
    funct7=7'b0000000; funct3=3'b011; #5;
    if(alu_control==4'b1001) $display("PASS : SLTU");
    else $display("FAIL : SLTU");

    //-------------------------
    // I-Type
    //-------------------------

    opcode=7'b0010011;

    funct3=3'b000; funct7=0; #5;
    if(alu_control==4'b0000) $display("PASS : ADDI");

    funct3=3'b111; funct7=0; #5;
    if(alu_control==4'b0010) $display("PASS : ANDI");

    funct3=3'b110; funct7=0; #5;
    if(alu_control==4'b0011) $display("PASS : ORI");

    funct3=3'b100; funct7=0; #5;
    if(alu_control==4'b0100) $display("PASS : XORI");

    funct3=3'b010; funct7=0; #5;
    if(alu_control==4'b1000) $display("PASS : SLTI");

    funct3=3'b011; funct7=0; #5;
    if(alu_control==4'b1001) $display("PASS : SLTIU");

    funct3=3'b001; funct7=7'b0000000; #5;
    if(alu_control==4'b0101) $display("PASS : SLLI");

    funct3=3'b101; funct7=7'b0000000; #5;
    if(alu_control==4'b0110) $display("PASS : SRLI");

    funct3=3'b101; funct7=7'b0100000; #5;
    if(alu_control==4'b0111) $display("PASS : SRAI");

    //-------------------------
    // LW
    //-------------------------

    opcode=7'b0000011;
    #5;
    if(alu_control==4'b0000)
        $display("PASS : LW");

    //-------------------------
    // SW
    //-------------------------

    opcode=7'b0100011;
    #5;
    if(alu_control==4'b0000)
        $display("PASS : SW");

    //-------------------------
    // Branch
    //-------------------------

    opcode=7'b1100011;

    funct3=3'b000; #5;
    if(alu_control==4'b0001)
        $display("PASS : BEQ");

    funct3=3'b001; #5;
    if(alu_control==4'b0001)
        $display("PASS : BNE");

    funct3=3'b100; #5;
    if(alu_control==4'b1000)
        $display("PASS : BLT");

    funct3=3'b101; #5;
    if(alu_control==4'b1000)
        $display("PASS : BGE");

    funct3=3'b110; #5;
    if(alu_control==4'b1001)
        $display("PASS : BLTU");

    funct3=3'b111; #5;
    if(alu_control==4'b1001)
        $display("PASS : BGEU");

    //-------------------------
    // Invalid opcode
    //-------------------------

    opcode=7'b1111111;
    #5;

    if(alu_control==4'b1111)
        $display("PASS : INVALID OPCODE");

    $display("----------------------------");
    $display("ALU CONTROL TEST COMPLETED");
    $display("----------------------------");

    $finish;

    end

endmodule

vcd/alu_control_tb.vcd
$date
	Thu Jul 02 13:42:18 2026
$end
$version
	Icarus Verilog
$end
$timescale
	1ps
$end
$scope module alu_control_tb $end
$var wire 4 ! alu_control [3:0] $end
$var reg 3 " funct3 [2:0] $end
$var reg 7 # funct7 [6:0] $end
$var reg 7 $ opcode [6:0] $end
$scope module dut $end
$var wire 3 % funct3 [2:0] $end
$var wire 7 & funct7 [6:0] $end
$var wire 7 ' opcode [6:0] $end
$var reg 4 ( alu_control [3:0] $end
$upscope $end
$upscope $end
$enddefinitions $end
#0
$dumpvars
b0 (
b110011 '
b0 &
b0 %
b110011 $
b0 #
b0 "
b0 !
$end
#5000
b1 (
b1 !
b100000 #
b100000 &
#10000
b10 (
b10 !
b111 "
b111 %
b0 #
b0 &
#15000
b11 (
b11 !
b110 "
b110 %
#20000
b100 (
b100 !
b100 "
b100 %
#25000
b101 (
b101 !
b1 "
b1 %
#30000
b110 (
b110 !
b101 "
b101 %
#35000
b111 (
b111 !
b100000 #
b100000 &
#40000
b1000 (
b1000 !
b10 "
b10 %
b0 #
b0 &
#45000
b1001 (
b1001 !
b11 "
b11 %
#50000
b0 (
b0 !
b0 "
b0 %
b10011 $
b10011 '
#55000
b10 (
b10 !
b111 "
b111 %
#60000
b11 (
b11 !
b110 "
b110 %
#65000
b100 (
b100 !
b100 "
b100 %
#70000
b1000 (
b1000 !
b10 "
b10 %
#75000
b1001 (
b1001 !
b11 "
b11 %
#80000
b101 (
b101 !
b1 "
b1 %
#85000
b110 (
b110 !
b101 "
b101 %
#90000
b111 (
b111 !
b100000 #
b100000 &
#95000
b0 (
b0 !
b11 $
b11 '
#100000
b100011 $
b100011 '
#105000
b1 (
b1 !
b0 "
b0 %
b1100011 $
b1100011 '
#110000
b1 (
b1 !
b1 "
b1 %
#115000
b1000 (
b1000 !
b100 "
b100 %
#120000
b1000 (
b1000 !
b101 "
b101 %
#125000
b1001 (
b1001 !
b110 "
b110 %
#130000
b1001 (
b1001 !
b111 "
b111 %
#135000
b1111 (
b1111 !
b1111111 $
b1111111 '
