rtl/data_memory.v
module data_memory(

    input clk,

    input [31:0] address,
    input [31:0] write_data,

    input mem_read,
    input mem_write,

    output reg [31:0] read_data

);

    // 256 words × 32 bits
    reg [31:0] dmem [0:255];

    //=========================
    // Write Logic (Sequential)
    //=========================
    always @(posedge clk) begin
        if (mem_write)
            dmem[address[31:2]] <= write_data;
    end

    //=========================
    // Read Logic (Combinational)
    //=========================
    always @(*) begin
        if (mem_read)
            read_data = dmem[address[31:2]];
        else
            read_data = 32'b0;
    end

endmodule

tb/module_tb/data_memory_tb.v
`timescale 1ns/1ps

module data_memory_tb;

reg         clk;
reg  [31:0] address;
reg  [31:0] write_data;
reg         mem_read;
reg         mem_write;

wire [31:0] read_data;

data_memory dut(
    .clk(clk),
    .address(address),
    .write_data(write_data),
    .mem_read(mem_read),
    .mem_write(mem_write),
    .read_data(read_data)
);

//-------------------------------------------------
// Clock Generation
//-------------------------------------------------

initial begin
    clk = 0;
    forever #5 clk = ~clk;
end

//-------------------------------------------------
// Dump Waveform
//-------------------------------------------------

initial begin
    $dumpfile("data_memory_tb.vcd");
    $dumpvars(0,data_memory_tb);
end

//-------------------------------------------------
// Monitor
//-------------------------------------------------

initial begin
    $monitor("T=%0t CLK=%b ADDR=%d WDATA=%d RDATA=%d MR=%b MW=%b",
             $time,
             clk,
             address,
             write_data,
             read_data,
             mem_read,
             mem_write);
end

//-------------------------------------------------
// Test Sequence
//-------------------------------------------------

initial begin

// Initialize
address    = 0;
write_data = 0;
mem_read   = 0;
mem_write  = 0;

//-------------------------------------------------
// Test 1 : Read Disabled
//-------------------------------------------------

#2;

if(read_data == 0)
    $display("PASS : Read Disabled");
else
    $display("FAIL : Read Disabled");

//-------------------------------------------------
// Test 2 : Write Address 100
//-------------------------------------------------

address    = 32'd100;
write_data = 32'd1234;
mem_write  = 1;

@(posedge clk);
#1;

mem_write = 0;

//-------------------------------------------------
// Test 3 : Read Address 100
//-------------------------------------------------

mem_read = 1;
#2;

if(read_data == 32'd1234)
    $display("PASS : Read Address 100");
else
    $display("FAIL : Read Address 100");

mem_read = 0;

//-------------------------------------------------
// Test 4 : Write Address 104
//-------------------------------------------------

address    = 32'd104;
write_data = 32'd999;
mem_write  = 1;

@(posedge clk);
#1;

mem_write = 0;

mem_read = 1;
#2;

if(read_data == 32'd999)
    $display("PASS : Read Address 104");
else
    $display("FAIL : Read Address 104");

mem_read = 0;

//-------------------------------------------------
// Test 5 : Verify Address 100 unchanged
//-------------------------------------------------

address  = 32'd100;
mem_read = 1;

#2;

if(read_data == 32'd1234)
    $display("PASS : Memory Isolation");
else
    $display("FAIL : Memory Isolation");

mem_read = 0;

//-------------------------------------------------
// Test 6 : Write Disabled
//-------------------------------------------------

address    = 32'd100;
write_data = 32'd7777;
mem_write  = 0;

@(posedge clk);

mem_read = 1;
#2;

if(read_data == 32'd1234)
    $display("PASS : Write Disabled");
else
    $display("FAIL : Write Disabled");

mem_read = 0;

//-------------------------------------------------
// Test 7 : Address Alignment
//-------------------------------------------------

address = 32'd101;
mem_read = 1;
#2;

if(read_data == 32'd1234)
    $display("PASS : Address 101");
else
    $display("FAIL : Address 101");

address = 32'd102;
#2;

if(read_data == 32'd1234)
    $display("PASS : Address 102");
else
    $display("FAIL : Address 102");

address = 32'd103;
#2;

if(read_data == 32'd1234)
    $display("PASS : Address 103");
else
    $display("FAIL : Address 103");

mem_read = 0;

//-------------------------------------------------
// Test 8 : Overwrite
//-------------------------------------------------

address    = 32'd100;
write_data = 32'd2222;
mem_write  = 1;

@(posedge clk);
#1;

mem_write = 0;

mem_read = 1;
#2;

if(read_data == 32'd2222)
    $display("PASS : Overwrite");
else
    $display("FAIL : Overwrite");

mem_read = 0;

//-------------------------------------------------
// Test 9 : Read Disabled Again
//-------------------------------------------------

#2;

if(read_data == 0)
    $display("PASS : Read Disabled Again");
else
    $display("FAIL : Read Disabled Again");

$display("--------------------------------");
$display("DATA MEMORY TEST COMPLETED");
$display("--------------------------------");

$finish;

end

endmodule

vcd/data_memory_tb.vcd
$date
	Thu Jul 02 14:40:11 2026
$end
$version
	Icarus Verilog
$end
$timescale
	1ps
$end
$scope module data_memory_tb $end
$var wire 32 ! read_data [31:0] $end
$var reg 32 " address [31:0] $end
$var reg 1 # clk $end
$var reg 1 $ mem_read $end
$var reg 1 % mem_write $end
$var reg 32 & write_data [31:0] $end
$scope module dut $end
$var wire 32 ' address [31:0] $end
$var wire 1 ( clk $end
$var wire 1 ) mem_read $end
$var wire 1 * mem_write $end
$var wire 32 + write_data [31:0] $end
$var reg 32 , read_data [31:0] $end
$upscope $end
$upscope $end
$enddefinitions $end
#0
$dumpvars
b0 ,
b0 +
0*
0)
0(
b0 '
b0 &
0%
0$
0#
b0 "
b0 !
$end
#2000
1%
1*
b10011010010 &
b10011010010 +
b1100100 "
b1100100 '
#5000
1#
1(
#6000
b10011010010 ,
b10011010010 !
1$
1)
0%
0*
#8000
b0 ,
b0 !
1%
1*
b1111100111 &
b1111100111 +
b1101000 "
b1101000 '
0$
0)
#10000
0#
0(
#15000
1#
1(
#16000
b1111100111 ,
b1111100111 !
1$
1)
0%
0*
#18000
b10011010010 ,
b10011010010 !
b1100100 "
b1100100 '
1$
1)
#20000
b0 ,
b0 !
b1111001100001 &
b1111001100001 +
0$
0)
0#
0(
#25000
b10011010010 ,
b10011010010 !
1$
1)
1#
1(
#27000
b1100101 "
b1100101 '
1$
1)
#29000
b1100110 "
b1100110 '
#30000
0#
0(
#31000
b1100111 "
b1100111 '
#33000
b0 ,
b0 !
1%
1*
b100010101110 &
b100010101110 +
b1100100 "
b1100100 '
0$
0)
#35000
1#
1(
#36000
b100010101110 ,
b100010101110 !
1$
1)
0%
0*
#38000
b0 ,
b0 !
0$
0)
