rtl/register_file.v
module register_file(
    input         clk,
    input         reg_write,

    input  [4:0]  rs1,
    input  [4:0]  rs2,
    input  [4:0]  rd,

    input  [31:0] write_data,

    output [31:0] read_data1,
    output [31:0] read_data2
);

reg [31:0] registers [0:31];

always @(posedge clk)begin
    if(reg_write && rd != 5'b0)
        registers[rd] <= write_data;
end

assign read_data1 = (rs1 == 0) ? 32'b0 : registers[rs1];
assign read_data2 = (rs2 == 0) ? 32'b0 : registers[rs2];

endmodule

tb/module_tb/register_file_tb.v
`timescale 1ns/1ps

module register_file_tb;

    //==================================================
    // Testbench Signals
    //==================================================

    reg         clk;
    reg         reg_write;

    reg  [4:0]  rs1;
    reg  [4:0]  rs2;
    reg  [4:0]  rd;

    reg  [31:0] write_data;

    wire [31:0] read_data1;
    wire [31:0] read_data2;

    //==================================================
    // DUT
    //==================================================

    register_file dut (
        .clk(clk),
        .reg_write(reg_write),
        .rs1(rs1),
        .rs2(rs2),
        .rd(rd),
        .write_data(write_data),
        .read_data1(read_data1),
        .read_data2(read_data2)
    );

    //==================================================
    // Clock Generation (10ns Period)
    //==================================================

    initial begin
        clk = 0;
        forever #5 clk = ~clk;
    end

    //==================================================
    // Waveform Dump
    //==================================================

    initial begin
        $dumpfile("register_file_tb.vcd");
        $dumpvars(1, register_file_tb);
    end

    //==================================================
    // Monitor
    //==================================================

    initial begin
        $monitor("T=%0t | WE=%b RD=%0d WD=%h | RS1=%0d RD1=%h | RS2=%0d RD2=%h",
                  $time,
                  reg_write,
                  rd,
                  write_data,
                  rs1,
                  read_data1,
                  rs2,
                  read_data2);
    end

    //==================================================
    // Stimulus
    //==================================================

    initial begin

        //------------------------------------------
        // Initialize
        //------------------------------------------

        reg_write  = 0;
        rs1        = 0;
        rs2        = 0;
        rd         = 0;
        write_data = 0;

        //------------------------------------------------
        // Test 1 : x0 always reads zero
        //------------------------------------------------

        #2;

        rs1 = 0;
        rs2 = 0;

        #1;

        if(read_data1 == 32'b0 && read_data2 == 32'b0)
            $display("PASS : x0 is hardwired to zero");
        else
            $display("FAIL : x0");

        //------------------------------------------------
        // Test 2 : Write x5 = 100
        //------------------------------------------------

        rd         = 5;
        write_data = 32'd100;
        reg_write  = 1;

        @(posedge clk);

        #1;

        reg_write = 0;

        rs1 = 5;

        #1;

        if(read_data1 == 32'd100)
            $display("PASS : Write/Read x5");
        else
            $display("FAIL : Write x5");

        //------------------------------------------------
        // Test 3 : Write x10 = 999
        //------------------------------------------------

        rd         = 10;
        write_data = 32'd999;
        reg_write  = 1;

        @(posedge clk);

        #1;

        reg_write = 0;

        rs1 = 10;

        #1;

        if(read_data1 == 32'd999)
            $display("PASS : Write/Read x10");
        else
            $display("FAIL : Write x10");

        //------------------------------------------------
        // Test 4 : Read two registers together
        //------------------------------------------------

        rs1 = 5;
        rs2 = 10;

        #1;

        if(read_data1 == 32'd100 &&
           read_data2 == 32'd999)
            $display("PASS : Dual Read");
        else
            $display("FAIL : Dual Read");

        //------------------------------------------------
        // Test 5 : reg_write = 0 (no write)
        //------------------------------------------------

        rd         = 5;
        write_data = 32'd555;
        reg_write  = 0;

        @(posedge clk);

        rs1 = 5;

        #1;

        if(read_data1 == 32'd100)
            $display("PASS : Write Disabled");
        else
            $display("FAIL : Write Disabled");

        //------------------------------------------------
        // Test 6 : Attempt to write x0
        //------------------------------------------------

        rd         = 0;
        write_data = 32'hFFFFFFFF;
        reg_write  = 1;

        @(posedge clk);

        #1;

        reg_write = 0;

        rs1 = 0;

        #1;

        if(read_data1 == 32'b0)
            $display("PASS : x0 Protected");
        else
            $display("FAIL : x0 Modified");

        //------------------------------------------------
        // Finish
        //------------------------------------------------

        #10;

        $display("---------------------------------------");
        $display("Register File Test Completed");
        $display("---------------------------------------");

        $finish;

    end

endmodule

vcd/register_file_tb.vcd
$date
	Wed Jul 01 22:32:44 2026
$end
$version
	Icarus Verilog
$end
$timescale
	1ps
$end
$scope module register_file_tb $end
$var wire 32 ! read_data1 [31:0] $end
$var wire 32 " read_data2 [31:0] $end
$var reg 1 # clk $end
$var reg 5 $ rd [4:0] $end
$var reg 1 % reg_write $end
$var reg 5 & rs1 [4:0] $end
$var reg 5 ' rs2 [4:0] $end
$var reg 32 ( write_data [31:0] $end
$scope module dut $end
$var wire 1 ) clk $end
$var wire 5 * rd [4:0] $end
$var wire 32 + read_data1 [31:0] $end
$var wire 32 , read_data2 [31:0] $end
$var wire 1 - reg_write $end
$var wire 5 . rs1 [4:0] $end
$var wire 5 / rs2 [4:0] $end
$var wire 32 0 write_data [31:0] $end
$upscope $end
$upscope $end
$enddefinitions $end
#0
$dumpvars
b0 0
b0 /
b0 .
0-
b0 ,
b0 +
b0 *
0)
b0 (
b0 '
b0 &
0%
b0 $
0#
b0 "
b0 !
$end
#3000
1%
1-
b1100100 (
b1100100 0
b101 $
b101 *
#5000
1#
1)
#6000
b1100100 !
b1100100 +
b101 &
b101 .
0%
0-
#7000
1%
1-
b1111100111 (
b1111100111 0
b1010 $
b1010 *
#10000
0#
0)
#15000
1#
1)
#16000
b1111100111 !
b1111100111 +
b1010 &
b1010 .
0%
0-
#17000
b1111100111 "
b1111100111 ,
b1100100 !
b1100100 +
b1010 '
b1010 /
b101 &
b101 .
#18000
b1000101011 (
b1000101011 0
b101 $
b101 *
#20000
0#
0)
#25000
1#
1)
#26000
1%
1-
b11111111111111111111111111111111 (
b11111111111111111111111111111111 0
b0 $
b0 *
#30000
0#
0)
#35000
1#
1)
#36000
b0 !
b0 +
b0 &
b0 .
0%
0-
